spider/__init__.py
spider/__main__.py
spider/proxy.py
spider_proxy-1.0.0.dist-info/METADATA
spider_proxy-1.0.0.dist-info/WHEEL
spider_proxy-1.0.0.dist-info/top_level.txt
spider_proxy-1.0.0.dist-info/RECORD
